{"line_number": 1034, "line_type": "original", "code": "", "entropy": 0.1978759765625, "is_bug_line": false, "sus_score": 0.6552679538726807, "per_token_entropy": [0.1978759765625], "tokens": [203]}
{"line_number": 1034, "line_type": "generated", "code": "", "entropy": "10", "is_bug_line": false, "sus_score": 0.6552679538726807, "per_token_entropy": [], "tokens": []}
{"line_number": 1033, "line_type": "original", "code": "", "entropy": 0.1978759765625, "is_bug_line": false, "sus_score": 0.6547810435295105, "per_token_entropy": [0.1978759765625], "tokens": [203]}
{"line_number": 1033, "line_type": "generated", "code": "", "entropy": "10", "is_bug_line": false, "sus_score": 0.6547810435295105, "per_token_entropy": [], "tokens": []}
{"line_number": 709, "line_type": "original", "code": "      if (isObjLit) {", "entropy": 1.9453125, "is_bug_line": false, "sus_score": 0.6487389206886292, "per_token_entropy": [5.68359375, 2.400390625, 0.261962890625, 3.091796875, 1.890625, 0.0142059326171875, 2.1953125, 0.0276336669921875], "tokens": [647, 415, 308, 297, 3273, 27472, 27, 301]}
{"line_number": 709, "line_type": "generated", "code": "\n    updateObjLitOrFunctionDeclaration(n, n.getAlias(), canCollapseChildNames);\n  }\n\n  /**\n   * Updates the first initialization (a.k.a \"declaration\") of a global name\n   * that occurs at an assignment node.", "entropy": 0.23486328125, "is_bug_line": false, "sus_score": 0.6487389206886292, "per_token_entropy": [0.2142333984375, 1.19140625, 0.047821044921875, 0.0048370361328125, 0.00322723388671875, 0.0027027130126953125, 0.005626678466796875, 0.0958251953125, 0.74609375, 0.033416748046875, 0.4609375, 0.0208587646484375, 0.67578125, 1.7763671875, 0.1986083984375, 0.57666015625, 3.2782554626464844e-05, 4.839897155761719e-05, 9.5367431640625e-07, 0.0225067138671875, 0.0811767578125, 0.0003116130828857422, 0.205810546875, 0.06414794921875, 0.01499176025390625, 4.1365623474121094e-05, 0.2296142578125, 0.328857421875, 0.2314453125, 0.0221099853515625, 0.08642578125, 0.004901885986328125, 5.8531761169433594e-05, 0.00018417835235595703, 1.823902130126953e-05, 0.0003190040588378906, 0.00537872314453125, 0.002925872802734375, 0.001438140869140625, 0.006999969482421875, 0.0362548828125, 0.08233642578125, 0.0165557861328125, 0.19140625, 7.987022399902344e-05, 0.111328125, 0.034454345703125, 0.56689453125, 1.13671875, 1.6376953125, 0.8544921875, 0.177001953125], "tokens": [284, 1974, 3273, 27472, 1527, 2447, 10367, 26, 96, 30, 310, 32, 371, 7886, 1026, 883, 28373, 2931, 4109, 293, 334, 320, 719, 1022, 664, 319, 19293, 322, 1932, 13577, 308, 83, 32, 93, 32, 83, 313, 24050, 657, 432, 312, 3649, 636, 664, 319, 688, 12984, 821, 600, 13807, 1541, 32]}
{"line_number": 1417, "line_type": "original", "code": "", "entropy": 0.1978759765625, "is_bug_line": false, "sus_score": 0.648590087890625, "per_token_entropy": [0.1978759765625], "tokens": [203]}
{"line_number": 1417, "line_type": "generated", "code": "", "entropy": "10", "is_bug_line": false, "sus_score": 0.648590087890625, "per_token_entropy": [], "tokens": []}
{"line_number": 1433, "line_type": "original", "code": "", "entropy": 0.1978759765625, "is_bug_line": false, "sus_score": 0.647622287273407, "per_token_entropy": [0.1978759765625], "tokens": [203]}
{"line_number": 1433, "line_type": "generated", "code": "", "entropy": "10", "is_bug_line": false, "sus_score": 0.647622287273407, "per_token_entropy": [], "tokens": []}
{"line_number": 2188, "line_type": "original", "code": "", "entropy": 0.1978759765625, "is_bug_line": false, "sus_score": 0.6433373093605042, "per_token_entropy": [0.1978759765625], "tokens": [203]}
{"line_number": 2188, "line_type": "generated", "code": "", "entropy": "10", "is_bug_line": false, "sus_score": 0.6433373093605042, "per_token_entropy": [], "tokens": []}
{"line_number": 1446, "line_type": "original", "code": "", "entropy": 0.1978759765625, "is_bug_line": false, "sus_score": 0.6359612941741943, "per_token_entropy": [0.1978759765625], "tokens": [203]}
{"line_number": 1446, "line_type": "generated", "code": "", "entropy": "10", "is_bug_line": false, "sus_score": 0.6359612941741943, "per_token_entropy": [], "tokens": []}
{"line_number": 1415, "line_type": "original", "code": "", "entropy": 0.1978759765625, "is_bug_line": false, "sus_score": 0.5874029397964478, "per_token_entropy": [0.1978759765625], "tokens": [203]}
{"line_number": 1415, "line_type": "generated", "code": "", "entropy": "10", "is_bug_line": false, "sus_score": 0.5874029397964478, "per_token_entropy": [], "tokens": []}
{"line_number": 1215, "line_type": "original", "code": "", "entropy": 0.1978759765625, "is_bug_line": false, "sus_score": 0.5852785706520081, "per_token_entropy": [0.1978759765625], "tokens": [203]}
{"line_number": 1215, "line_type": "generated", "code": "", "entropy": "10", "is_bug_line": false, "sus_score": 0.5852785706520081, "per_token_entropy": [], "tokens": []}
{"line_number": 1916, "line_type": "original", "code": "", "entropy": 0.1978759765625, "is_bug_line": false, "sus_score": 0.5839114785194397, "per_token_entropy": [0.1978759765625], "tokens": [203]}
{"line_number": 1916, "line_type": "generated", "code": "", "entropy": "10", "is_bug_line": false, "sus_score": 0.5839114785194397, "per_token_entropy": [], "tokens": []}
{"line_number": 830, "line_type": "original", "code": "      Name objlitName, String alias, Node objlit, Node varNode,", "entropy": 1.8544921875, "is_bug_line": false, "sus_score": 0.5835248231887817, "per_token_entropy": [2.783203125, 6.48828125, 7.1015625, 0.25439453125, 0.3896484375, 2.62890625, 3.181640625, 2.23828125, 0.62890625, 1.51171875, 1.822265625, 0.004871368408203125, 0.28173828125, 0.71142578125, 0.80615234375, 0.287841796875, 0.412841796875], "tokens": [647, 3270, 2830, 2507, 558, 30, 892, 8813, 30, 4004, 2830, 2507, 30, 4004, 773, 1212, 30]}
{"line_number": 830, "line_type": "generated", "code": "\n      if (isJsIdentifier) {\n        nameNode.setJSType(key.getJSType());\n      }", "entropy": 0.40234375, "is_bug_line": false, "sus_score": 0.5835248231887817, "per_token_entropy": [0.2362060546875, 1.4033203125, 0.35693359375, 2.201171875, 0.2301025390625, 0.0012025833129882812, 0.11517333984375, 0.047698974609375, 0.1513671875, 0.5390625, 0.010986328125, 0.034515380859375, 1.0595703125, 1.259765625, 0.004360198974609375, 0.013092041015625, 1.7626953125, 0.005939483642578125, 0.01064300537109375, 0.0004215240478515625, 1.33514404296875e-05, 0.0162200927734375, 0.198974609375, 9.66787338256836e-05], "tokens": [397, 415, 308, 297, 10535, 5541, 27, 301, 291, 636, 1212, 32, 470, 4624, 620, 26, 678, 32, 371, 4624, 620, 1035, 397, 320]}
{"line_number": 1007, "line_type": "original", "code": "", "entropy": 0.1978759765625, "is_bug_line": false, "sus_score": 0.5831325054168701, "per_token_entropy": [0.1978759765625], "tokens": [203]}
{"line_number": 1007, "line_type": "generated", "code": "", "entropy": "10", "is_bug_line": false, "sus_score": 0.5831325054168701, "per_token_entropy": [], "tokens": []}
{"line_number": 1014, "line_type": "original", "code": "", "entropy": 0.1978759765625, "is_bug_line": false, "sus_score": 0.5820755958557129, "per_token_entropy": [0.1978759765625], "tokens": [203]}
{"line_number": 1014, "line_type": "generated", "code": "", "entropy": "10", "is_bug_line": false, "sus_score": 0.5820755958557129, "per_token_entropy": [], "tokens": []}
{"line_number": 1023, "line_type": "original", "code": "", "entropy": 0.1978759765625, "is_bug_line": false, "sus_score": 0.5815074443817139, "per_token_entropy": [0.1978759765625], "tokens": [203]}
{"line_number": 1023, "line_type": "generated", "code": "", "entropy": "10", "is_bug_line": false, "sus_score": 0.5815074443817139, "per_token_entropy": [], "tokens": []}
{"line_number": 839, "line_type": "original", "code": "      nextKey = key.getNext();", "entropy": 1.82421875, "is_bug_line": false, "sus_score": 0.5812672972679138, "per_token_entropy": [3.904296875, 9.390625, 0.5458984375, 0.072998046875, 0.5263671875, 0.133544921875, 0.00637054443359375, 0.01049041748046875], "tokens": [647, 2354, 953, 280, 1202, 32, 23017, 473]}
{"line_number": 839, "line_type": "generated", "code": "\n        varParent.addChildToFront(newVar);\n      }\n      numVars++;", "entropy": 0.1395263671875, "is_bug_line": false, "sus_score": 0.5812672972679138, "per_token_entropy": [0.28076171875, 0.11767578125, 0.55615234375, 0.00011277198791503906, 0.0003578662872314453, 0.0035266876220703125, 0.37353515625, 0.0002548694610595703, 0.001705169677734375, 2.8967857360839844e-05, 0.003566741943359375, 0.2164306640625, 9.953975677490234e-05, 0.326416015625, 0.452880859375, 0.0010461807250976562, 0.035614013671875], "tokens": [291, 773, 4433, 32, 21545, 705, 10112, 26, 890, 1881, 293, 397, 320, 397, 1929, 12034, 3334]}
{"line_number": 376, "line_type": "original", "code": "", "entropy": 3.29296875, "is_bug_line": false, "sus_score": 0.5810549855232239, "per_token_entropy": [3.29296875], "tokens": [203]}
{"line_number": 376, "line_type": "generated", "code": "\n  /**\n   * Flattens a name reference at a particular depth.\n   *\n   * @param alias A flattened prefix name (e.g. \"a$b\")\n   * @param n A name reference (e.g. \"a", "entropy": 0.25341796875, "is_bug_line": false, "sus_score": 0.5810549855232239, "per_token_entropy": [0.473876953125, 0.1785888671875, 0.0245361328125, 0.00017154216766357422, 0.521484375, 0.00014472007751464844, 3.743171691894531e-05, 0.369873046875, 1.177734375, 0.323486328125, 2.34765625, 0.1304931640625, 0.66943359375, 0.04046630859375, 0.552734375, 0.37060546875, 0.06390380859375, 0.298828125, 0.0010576248168945312, 0.2044677734375, 0.0030078887939453125, 0.35986328125, 0.46142578125, 0.10858154296875, 0.0010013580322265625, 0.457275390625, 0.040740966796875, 0.06475830078125, 0.0013484954833984375, 0.0001264810562133789, 0.0005254745483398438, 0.0011224746704101562, 0.006191253662109375, 0.005588531494140625, 0.005519866943359375, 0.00197601318359375, 0.13134765625, 0.0015964508056640625, 0.0012006759643554688, 0.00030684471130371094, 0.00037384033203125, 0.7861328125, 0.354248046875, 1.005859375, 0.568359375, 0.7509765625, 0.0248870849609375, 0.0007419586181640625, 0.0010805130004882812, 0.010498046875, 0.1915283203125, 0.07537841796875], "tokens": [334, 1022, 664, 319, 5449, 3131, 1229, 312, 636, 4121, 821, 312, 8409, 7713, 32, 664, 319, 664, 319, 477, 753, 8813, 399, 21096, 318, 5202, 636, 308, 87, 32, 89, 32, 313, 83, 22, 84, 657, 664, 319, 477, 753, 310, 399, 636, 4121, 308, 87, 32, 89, 32, 313, 83]}
{"line_number": 1445, "line_type": "original", "code": "", "entropy": 0.1978759765625, "is_bug_line": false, "sus_score": 0.5772095918655396, "per_token_entropy": [0.1978759765625], "tokens": [203]}
{"line_number": 1445, "line_type": "generated", "code": "", "entropy": "10", "is_bug_line": false, "sus_score": 0.5772095918655396, "per_token_entropy": [], "tokens": []}
{"line_number": 1444, "line_type": "original", "code": "", "entropy": 0.1978759765625, "is_bug_line": false, "sus_score": 0.5768963098526001, "per_token_entropy": [0.1978759765625], "tokens": [203]}
{"line_number": 1444, "line_type": "generated", "code": "", "entropy": "10", "is_bug_line": false, "sus_score": 0.5768963098526001, "per_token_entropy": [], "tokens": []}
{"line_number": 459, "line_type": "original", "code": "   * @param parent {@code n}'s parent", "entropy": 2.146484375, "is_bug_line": false, "sus_score": 0.5688289403915405, "per_token_entropy": [6.421875, 4.41796875, 2.4765625, 0.033782958984375, 4.375, 4.86328125, 0.0648193359375, 0.226806640625, 0.443603515625, 0.00037550926208496094, 0.281982421875], "tokens": [261, 319, 477, 753, 2935, 3088, 687, 310, 8129, 101, 2935]}
{"line_number": 459, "line_type": "generated", "code": "\n            p, alias);\n      }\n    }\n  }\n\n  /**\n   * Updates a name node corresponding to a function declaration or a\n   * property of an object literal.\n   *\n   * @param n A name node\n   * @param alias The flattened", "entropy": 0.53173828125, "is_bug_line": false, "sus_score": 0.5688289403915405, "per_token_entropy": [1.2275390625, 0.125, 0.13037109375, 0.62060546875, 0.53955078125, 0.342529296875, 3.7670135498046875e-05, 0.061431884765625, 0.0001666545867919922, 0.1297607421875, 0.0007724761962890625, 0.1064453125, 0.128173828125, 0.024200439453125, 9.417533874511719e-05, 1.326171875, 0.84716796875, 2.10546875, 1.26171875, 3.27734375, 0.01373291015625, 0.4921875, 2.169921875, 1.1435546875, 0.419921875, 1.5244140625, 0.490966796875, 6.16312026977539e-05, 2.607421875, 1.017578125, 0.27197265625, 0.09918212890625, 0.00948333740234375, 1.34375, 0.324462890625, 0.046478271484375, 0.08282470703125, 0.0001920461654663086, 0.170654296875, 0.0037174224853515625, 0.0672607421875, 0.370849609375, 1.2578125, 0.112548828125, 0.9912109375, 0.006336212158203125, 0.0010814666748046875, 0.001972198486328125, 0.0275115966796875, 0.2332763671875, 0.08929443359375, 0.0004944801330566406], "tokens": [324, 298, 30, 8813, 293, 397, 320, 284, 320, 334, 320, 719, 1022, 664, 319, 19293, 312, 636, 1541, 8435, 372, 312, 667, 13317, 556, 312, 664, 319, 2804, 432, 600, 1300, 10652, 32, 664, 319, 664, 319, 477, 753, 310, 399, 636, 1541, 664, 319, 477, 753, 8813, 886, 21096, 318]}
{"line_number": 1022, "line_type": "original", "code": "", "entropy": 0.1978759765625, "is_bug_line": false, "sus_score": 0.5660623908042908, "per_token_entropy": [0.1978759765625], "tokens": [203]}
{"line_number": 1022, "line_type": "generated", "code": "", "entropy": "10", "is_bug_line": false, "sus_score": 0.5660623908042908, "per_token_entropy": [], "tokens": []}
{"line_number": 1032, "line_type": "original", "code": "", "entropy": 0.1978759765625, "is_bug_line": false, "sus_score": 0.562140166759491, "per_token_entropy": [0.1978759765625], "tokens": [203]}
{"line_number": 1032, "line_type": "generated", "code": "", "entropy": "10", "is_bug_line": false, "sus_score": 0.562140166759491, "per_token_entropy": [], "tokens": []}
